<?xml version="1.0" encoding="UTF-8"?>
<root>
     <tables>      
        <table id="GIS_LX" rowStart="7"  totalRows="0" className="com.hdsx.test.bean.GISLx" PKFieldsShape="LXBM;ZDZH"  PKFieldsExcel="路线编号;止点桩号"  >
                <column cellType="string"  cellCode="cell_0" cellName="路线编号"     field="LXDM"/>
                <column cellType="string"  cellCode="cell_1" cellName="所在行政区划"  field="XZQHBM"/>
                <column cellType="string"  cellCode="cell_2" cellName="路线名称"     field="LXMC"/>
                <column cellType="string"  cellCode="cell_3" cellName="起点名称"     field="QDMC"/>
                <column cellType="string"  cellCode="cell_4" cellName="止点名称"     field="ZDMC"/>
                <column cellType="double"  cellCode="cell_5" cellName="起点桩号"     field="QDZH"/>
                <column cellType="double"  cellCode="cell_6" cellName="止点桩号"     field="ZDZH"/>
                <column cellType="double"  cellCode="cell_7" cellName="里程"        field="LC"/>
                <column cellType="string"  cellCode="cell_9" cellName="技术等级"     field="JSDJ"/>
                <column cellType="string"  cellCode="cell_10" cellName="是否一副高速"     field="LDJSDJBMBM"/>
                <column cellType="string"  cellCode="cell_12" cellName="车道数量"     field="LDCDSLBMBM"/>
                <column cellType="string"  cellCode="cell_14" cellName="面层类型"     field="LDMCLXDM"/>
                <column cellType="double"  cellCode="cell_15" cellName="路基宽度"     field="LDLJKD"/>
                <column cellType="double"  cellCode="cell_16" cellName="路面宽度"     field="LDLMKD"/>
                <column cellType="double"  cellCode="cell_17" cellName="设计时速"     field="LDSJSS"/>
                
                <column cellType="string"  cellCode="cell_18" cellName="修建年度"     field="YJND"/>
                <column cellType="string"  cellCode="cell_20" cellName="锻炼类型"     field="DLLXBM"/>
                <column cellType="string"  cellCode="cell_24" cellName="重复路线编号"     field="FLLXDM"/>
                <column cellType="string"  cellCode="cell_30" cellName="地貌"     field="DMDM"/>
        </table>
		   <!-- GIS桥梁 -->
        <table id="GIS_QL" rowStart="7"  totalRows="0" className="com.hdsx.giscj.zygzw.bean.GisQl">
                <column cellType="string"  cellCode="cell_0"  cellName="桥梁代码"    field="QLMC"/>
                <column cellType="string"  cellCode="cell_1"  cellName="桥梁名称"    field="QLDM"/>
                <column cellType="double"  cellCode="cell_2"  cellName="桥梁中心桩号"    field="QLZXZH"/>
                <column cellType="string"  cellCode="cell_3"  cellName="路线代码"    field="LXDM"/>
                <column cellType="double"  cellCode="cell_6"  cellName="桥梁全长"    field="QLQC"/>
                <column cellType="double"  cellCode="cell_10"  cellName="桥面全宽"    field="QMQK"/>
                <column cellType="double"  cellCode="cell_11"  cellName="桥面净宽"    field="QMJK"/>
                <column cellType="string"  cellCode="cell_13"  cellName="桥梁跨径分类编目编码"    field="QLKJFLBMBM"/>
                <column cellType="string"  cellCode="cell_15" cellName="按使用年限分类编目编码"    field="ASYNXFLBMBM"/>
                <column cellType="string"  cellCode="cell_23"  cellName="设计荷载等级编目编码"    field="SJHZDJBMBM"/>
                <column cellType="string"  cellCode="cell_44"  cellName="桥梁技术状况评定编目编码"    field="QLJSZKPDDM"/>
        </table>
</tables>  
</root>